maid_lsp/__init__.py
maid_lsp/__main__.py
maid_lsp/server.py
maid_lsp/capabilities/__init__.py
maid_lsp/capabilities/code_actions.py
maid_lsp/capabilities/diagnostics.py
maid_lsp/capabilities/hover.py
maid_lsp/utils/__init__.py
maid_lsp/utils/debounce.py
maid_lsp/validation/__init__.py
maid_lsp/validation/models.py
maid_lsp/validation/parser.py
maid_lsp/validation/runner.py
maid_lsp-0.1.10.dist-info/METADATA
maid_lsp-0.1.10.dist-info/WHEEL
maid_lsp-0.1.10.dist-info/entry_points.txt
maid_lsp-0.1.10.dist-info/RECORD
