Metadata-Version: 2.4
Name: maid-lsp
Version: 0.1.10
Summary: Language Server Protocol implementation for MAID methodology validation
Project-URL: Homepage, https://github.com/mamertofabian/maid-lsp
Project-URL: Documentation, https://github.com/mamertofabian/maid-lsp#readme
Project-URL: Repository, https://github.com/mamertofabian/maid-lsp
Project-URL: Issues, https://github.com/mamertofabian/maid-lsp/issues
Author-email: "Mamerto Fabian Jr." <mamerto@codefrost.dev>
License: MIT
Keywords: language-server,lsp,maid,manifest,validation
Classifier: Development Status :: 3 - Alpha
Classifier: Environment :: Console
Classifier: Intended Audience :: Developers
Classifier: License :: OSI Approved :: MIT License
Classifier: Operating System :: OS Independent
Classifier: Programming Language :: Python :: 3
Classifier: Programming Language :: Python :: 3.10
Classifier: Programming Language :: Python :: 3.11
Classifier: Programming Language :: Python :: 3.12
Classifier: Topic :: Software Development :: Quality Assurance
Classifier: Topic :: Text Editors :: Integrated Development Environments (IDE)
Requires-Python: >=3.10
Requires-Dist: lsprotocol>=2023.0.1
Requires-Dist: maid-runner>=0.11.4
Requires-Dist: pygls>=1.3.0
Provides-Extra: dev
Requires-Dist: black>=24.0.0; extra == 'dev'
Requires-Dist: mypy>=1.8.0; extra == 'dev'
Requires-Dist: pre-commit>=3.6.0; extra == 'dev'
Requires-Dist: pytest-asyncio>=0.23.0; extra == 'dev'
Requires-Dist: pytest-cov>=4.1.0; extra == 'dev'
Requires-Dist: pytest>=8.0.0; extra == 'dev'
Requires-Dist: ruff>=0.3.0; extra == 'dev'
